serraict_sqlalchemy_dremio-3.0.6.dist-info/licenses/LICENSE
sqlalchemy_dremio/__init__.py
sqlalchemy_dremio/base.py
sqlalchemy_dremio/db.py
sqlalchemy_dremio/exceptions.py
sqlalchemy_dremio/flight.py
sqlalchemy_dremio/flight_middleware.py
sqlalchemy_dremio/query.py
serraict_sqlalchemy_dremio-3.0.6.dist-info/METADATA
serraict_sqlalchemy_dremio-3.0.6.dist-info/WHEEL
serraict_sqlalchemy_dremio-3.0.6.dist-info/entry_points.txt
serraict_sqlalchemy_dremio-3.0.6.dist-info/top_level.txt
serraict_sqlalchemy_dremio-3.0.6.dist-info/RECORD
