Metadata-Version: 2.4
Name: serraict-sqlalchemy-dremio
Version: 3.0.6
Summary: A SQLAlchemy dialect for Dremio via the Flight interface.
Home-page: https://github.com/serraict/sqlalchemy_dremio
Author: Marijn van der Zee
Author-email: marijn@serraict.com
License: Apache Software License
Keywords: sqlalchemy_dremio
Classifier: Development Status :: 5 - Production/Stable
Classifier: Intended Audience :: Developers
Classifier: License :: OSI Approved :: Apache Software License
Classifier: Natural Language :: English
Classifier: Programming Language :: Python :: 3
Classifier: Programming Language :: Python :: 3.7
License-File: LICENSE
Requires-Dist: SQLAlchemy<2.0,>=1.4
Requires-Dist: pyarrow~=20.0.0
Dynamic: author
Dynamic: author-email
Dynamic: classifier
Dynamic: description
Dynamic: description-content-type
Dynamic: home-page
Dynamic: keywords
Dynamic: license
Dynamic: license-file
Dynamic: requires-dist
Dynamic: summary
